useful_blockchain/__init__.py
useful_blockchain/blockchain.py
useful_blockchain-0.1.0.dist-info/LICENSE
useful_blockchain-0.1.0.dist-info/METADATA
useful_blockchain-0.1.0.dist-info/WHEEL
useful_blockchain-0.1.0.dist-info/top_level.txt
useful_blockchain-0.1.0.dist-info/RECORD
