Metadata-Version: 2.1
Name: useful_blockchain
Version: 0.1.0
Summary: Easy Blockchain: A simple blockchain implementation in Python.
Home-page: https://github.com/T3pp31/easyblockchain
Download-URL: https://github.com/T3pp31/easyblockchain
Author: Teppei Fukutomi
Author-email: ttyn4519@outlook.jp
Maintainer: Teppei Fukutomi
Maintainer-email: ttyn4519@outlook.jp
License: MIT
Classifier: Programming Language :: Python :: 3
Classifier: License :: OSI Approved :: MIT License
Classifier: Operating System :: OS Independent
Classifier: Topic :: Software Development :: Libraries :: Python Modules
Requires-Python: >=3.9
License-File: LICENSE
Requires-Dist: hashlib
Requires-Dist: json
Requires-Dist: datetime
Requires-Dist: os
